Workbook

Sheet Assumptions
A1: title | B1: metric | C1: value | D1: unit | E1: source | F1: confidence | G1: notes
A2: Red Notice | B2: Production Budget | C2: 200000000 | D2: $ | E2: the-numbers | F2: Medium | G2: estimate ranges from $150M (The Numbers) to $300M (director's own account Screenrant reporting)
A3: Extraction | B3: Production Budget | C3: 65000000 | D3: $ | E3: the-numbers | F3: High | G3: IMDB, Wikipedia, Moviefone
A4: The Super Mario Bros Movie | B4: Production Budget | C4: 100000000 | D4: $ | E4: the-numbers | F4: High | G4: financed by Illumination/ Universal not Netflix
A5: Red Notice | B5: Total Hours Viewed | C5: 454200000 | D5: hours | E5: Netflix Tudum (via CBR, Collider) | F5: Medium | G5: First 91 days, all-time ranking; secondhand via press citing Tudum's official data
A6: Red Notice | B6: Total Views | C6: 230900000 | D6: views | E6: Netflix Tudum (via CBR, Collider) | F6: Medium | G6: First 91 days; corroborated across two outlets
A7: Extraction | B7: Total Hours Viewed | C7: 266900000 | D7: hours | E7: Netflix Tudum (via What's on Netflix) | F7: Medium | G7: First 91 days
A8: Extraction | B8: Total Views | C8: 135700000 | D8: views | E8: Netflix Tudum (via What's on Netflix) | F8: Medium | G8: First 91 days
A9: Extraction 2 | B9: Total Hours Viewed (Actual) | C9: 278700000 | D9: hours | E9: Netflix Tudum (via What's on Netflix) | F9: Medium | G9: Franchise continuation outcome — used to validate the Extraction greenlight decision
A10: Extraction 2 | B10: Total Views (Actual) | C10: 134900000 | D10: views | E10: Netflix Tudum (via What's on Netflix) | F10: Medium
A11: The Super Mario Bros Movie | B11: World Wide Box Office | C11: 1359226275 | D11: $ | E11: The Numbers | F11: High | G11: Confirmed figure, audited box office data
A12: Netflix | B12: Full Year 2025 Revenue | C12: 45183000000 | D12: $ | E12: 10-K | F12: High | G12: FY2025, filed Jan 23 2026
A13: Netflix | B13: Global Paid Memberships | C13: 325000000 | D13: members | E13: Q4'25 Shareholder Letter | F13: High | G13: Over 325M - crossed milestone during Q4'25
A14: Netflix | B14: H2 2025 Hours Viewed (platform-wide) | C14: 96000000000 | D14: hours | E14: Q4'25 Shareholder Letter | F14: High | G14: Bi-annual Engagement Report figure, H2 2025
A15: Carry-On | B15: Production Budget | C15: 47000000 | D15: $ | E15: Wikipedia, IMDb | F15: High | G15: Confirmed across two independent sources Decision Title vs. Comparable
A16: Carry-On | B16: Total Hours Viewed | C16: 344100000 | D16: hours | E16: Netflix Tudum (via Collider) | F16: Medium | G16: First 91 days, all-time ranking; secondhand via press citing Tudum's official data Confirmed across two independent sources Decision Title vs. Comparable
A17: Carry-On | B17: Total Views | C17: 172100000 | D17: views | E17: Netflix Tudum (via Collider) | F17: Medium | G17: First 91 days Confirmed across two independent sources Decision Title vs. Comparable
A18: The Super Mario Bros Movie | B18: Netflix Hours Viewed (Debut Week) | C18: 4800000 | D18: hours | E18: Netflix Tudum (via ScreenRant) | F18: Medium | G18: Nov 27-Dec 3 2023, global, ranked #9
A19: The Super Mario Bros Movie | B19: Netflix Hours Viewed (First 8 Weeks, Cumulative) | C19: 6500000 | D19: hours | E19: Netflix Tudum (via ScreenRant) | F19: Medium | G19: Global, through late Jan 2024
A20: The Super Mario Bros Movie | B20: Netflix Hours Viewed (Calendar Year 2024, US only) | C20: 195300000 | D20: hours | E20: Statista/Nielsen | F20: Medium | G20: 11.72B minutes; excludes Dec 2023 launch month and all non-US viewing
A21: The Super Mario Bros Movie | B21: Netflix Top 10 Duration | C21: 38 | D21: weeks | E21: Comcast/UFEG Press Release | F21: High | G21: Primary source, direct from Netflix/Universal joint announcement; record-setting run, Dec 2023-Oct 2024
A22: The Super Mario Bros Movie | B22: Total Hours Viewed | C22: N/A (see itemized rows below) | D22: hours | E22: — | F22: — | G22: Correction: title WAS licensed to Netflix (Dec 2023-Oct 2024) via the Illumination/DreamWorks UFEG deal; real engagement data exists and is itemized below (rows 18-21). Original licensing/streaming-rights decision methodology retained since this remains fundamentally an acquisition decision; itemized hours now serve as actual-outcome validation, parallel to Extraction 2's role for the Extraction decision.
A23: The Gray Man | B23: Production Budget | C23: 200000000 | D23: $ | E23: Wikipedia | F23: High | G23: Confirmed, matches Red Notice as Netflix's joint-most-expensive original at time of release; Comparable for Red Notice forecast
A24: The Gray Man | B24: Total Hours Viewed | C24: 299500000 | D24: hours | E24: Wikipedia (List of most-watched Netflix original programming, sourced from Netflix Tudum) | F24: High | G24: First 91 days, current methodology; resolves earlier 28-day data mismatch; Comparable for Red Notice forecast
A25: The Gray Man | B25: Total Views | C25: 139300000 | D25: views | E25: Wikipedia (List of most-watched Netflix original programming, sourced from Netflix Tudum) | F25: High | G25: First 91 days; Comparable for Red Notice forecast
A26: KPop Demon Hunters | B26: Production Budget | C26: 100000000 | D26: $ | E26: Wikipedia, IMDb, Hollywood Reporter | F26: High | G26: Confirmed across multiple sources; Netflix committed to reimburse full production budget plus capped premium under 2021 direct-to-platform deal; Comparable for Red Notice forecast
A27: KPop Demon Hunters | B27: Total Hours Viewed | C27: 541800000 | D27: hours | E27: Wikipedia (List of most-watched Netflix original programming, sourced from Netflix Tudum) | F27: High | G27: First 91 days; Comparable for Red Notice forecast
A28: KPop Demon Hunters | B28: Total Views | C28: 325100000 | D28: views | E28: Wikipedia (List of most-watched Netflix original programming, sourced from Netflix Tudum) | F28: High | G28: First 91 days; Comparable for Red Notice forecast
A29: Bird Box | B29: Production Budget | C29: 19800000 | D29: $ | E29: Wikipedia | F29: High | G29: Confirmed; Comparable for Red Notice forecast
A30: Bird Box | B30: Total Hours Viewed | C30: 325300000 | D30: hours | E30: Wikipedia (List of most-watched Netflix original programming, sourced from Netflix Tudum) | F30: High | G30: First 91 days; Comparable for Red Notice forecast
A31: Bird Box | B31: Total Views | C31: 157400000 | D31: views | E31: Wikipedia (List of most-watched Netflix original programming, sourced from Netflix Tudum) | F31: High | G31: First 91 days; Comparable for Red Notice forecast
A32: Don't Look Up | B32: Production Budget | C32: 75000000 | D32: $ | E32: Wikipedia | F32: Medium | G32: Some outlets estimate up to $110M including star salaries; using Wikipedia's official figure for consistency; Comparable for Red Notice forecast
A33: Don't Look Up | B33: Total Hours Viewed | C33: 408600000 | D33: hours | E33: Wikipedia (List of most-watched Netflix original programming, sourced from Netflix Tudum) | F33: High | G33: First 91 days; Comparable for Red Notice forecast
A34: Don't Look Up | B34: Total Views | C34: 171400000 | D34: views | E34: Wikipedia (List of most-watched Netflix original programming, sourced from Netflix Tudum) | F34: High | G34: First 91 days; Comparable for Red Notice forecast
... A43: Back in Action | B43: Total Views | C43: 147200000 | D43: views | E43: Wikipedia (List of most-watched Netflix original programming, sourced from Netflix Tudum) | F43: High | G43: First 91 days; Comparable for Red Notice forecast
A44: Leave the World Behind | B44: Production Budget | C44: N/A | D44: $ | E44: — | F44: — | G44: No reliable source found; single unattributed estimate (~$70M) does not meet Medium confidence threshold; excluded from comp set
A45: Leave the World Behind | B45: Total Hours Viewed | C45: 339300000 | D45: hours | E45: Wikipedia (List of most-watched Netflix original programming, sourced from Netflix Tudum) | F45: High | G45: First 91 days; NOT used as comp due to missing budget data
A46: Leave the World Behind | B46: Total Views | C46: 143400000 | D46: views | E46: Wikipedia (List of most-watched Netflix original programming, sourced from Netflix Tudum) | F46: High | G46: First 91 days; NOT used as comp due to missing budget data
A89: I

Sheet Metrics
A1: Metric | B1: Value | D1: Source
A2: Beta | B2: =SLOPE(nflx_5yr_monthly!G3:G60, SP500_fred_5yr!C3:C60) -> 1.5262505 | D2: Calculated from monthly returns from S&P 500 and Netflix 5YR historical data
A3: Alpha | B3: =INTERCEPT(nflx_5yr_monthly!G3:G60, SP500_fred_5yr!C3:C60) -> -0.0039563144 | D3: Calculated from monthly returns from S&P 500 and Netflix 5YR historical data
A4: R^2 | B4: =RSQ(nflx_5yr_monthly!G2:G60,SP500_fred_5yr!C2:C60) -> 0.28419368 | D4: Calculated from monthly returns from S&P 500 and Netflix 5YR historical data
A5: Correlation | B5: =CORREL(nflx_5yr_monthly!G2:G60,SP500_fred_5yr!C2:C60) -> 0.53309819 | D5: Calculated from monthly returns from S&P 500 and Netflix 5YR historical data
A7: Risk Free Rate | B7: 0.0465 | D7: FRED
A8: Equity Risk Premium | B8: 0.0423 | D8: Damodaran Implied ERP (historical series)
A10: Cost of Equity | B10: =B7+(B2*B8) -> 0.1110604
A12: Shares outstanding | B12: 4163939676 | D12: 10-Q
A13: Current Share Price | B13: 74.14 | D13: NASDAQ August 10, 2026
A15: Market Value of Equity | B15: =B12*B13 -> 3.0871449e+11 | D15: Calculated from shares outstanding and current market share
A17: Market Value of Debt | B17: 14309000000 | D17: 10-Q
A19: Corporate Tax Rate | B19: 0.18 | D19: 10-Q
A22: Tranche | B22: Coupon | C22: Principal ($M) | D22: 10-Q
A23: 4.375% Senior Notes | B23: 0.04375 | C23: 1000 | D23: 10-Q
A24: 3.625% Senior Notes (2027) | B24: 0.03625 | C24: 1486 | D24: 10-Q
A25: 4.875% Senior Notes (2028) | B25: 0.04875 | C25: 1600 | D25: 10-Q
A26: 5.875% Senior Notes | B26: 0.05875 | C26: 1900 | D26: 10-Q
A27: 4.625% Senior Notes | B27: 0.04625 | C27: 1257 | D27: 10-Q
A28: 6.375% Senior Notes | B28: 0.06375 | C28: 800 | D28: 10-Q
A29: 3.875% Senior Notes | B29: 0.03875 | C29: 1372 | D29: 10-Q
A30: 5.375% Senior Notes | B30: 0.05375 | C30: 900 | D30: 10-Q
A31: 3.625% Senior Notes (2030) | B31: 0.03625 | C31: 1257 | D31: 10-Q
A32: 4.875% Senior Notes (2030) | B32: 0.04875 | C32: 1000 | D32: 10-Q
A33: 4.900% Senior Notes | B33: 0.049 | C33: 1000 | D33: 10-Q
A34: 5.400% Senior Notes | B34: 0.054 | C34: 800 | D34: 10-Q
A37: Cost of Debt (pre-tax) | B37: =SUMPRODUCT(B23:B34,C23:C34)/SUM(C23:C34) -> 0.047622808 | D37: Calculated from coupon and principal
A38: Cost of Debt (after-tax) | B38: =B37*(1-0.18) -> 0.039050703 | D38: Calculated from coupon and principal
A42: WACC | B42: =(B15/(B15+B17))*B10+(B17/(B15+B17))*B38 -> 0.10787058
A44: Weight of Equity | B44: =B15/(B15+B17) -> 0.95570291 | D44: Calculated using market value of equity and market value of debt
A45: Weight of Debt | B45: =B17/(B15+B17) -> 0.044297088 | D45: Calculated using market value of equity and market value of debt
A48: Global ARPU | B48: =(Assumptions!C12/Assumptions!C13)/12 -> 11.585385 | D48: Calculated taking revenue divided by membership divided by 12
A49: Avg Hours per Member | B49: =Assumptions!C14/(Assumptions!C13*6) -> 49.230769 | D49: Calculated taking platform hours divided by membership divided by 6
A50: Value Per Hour | B50: =B48/B49 -> 0.23532812 | D50: Calculated by dividing global ARPU by avg hours per month

Sheet nflx_5yr_monthly
A1: Date | B1: Open | C1: High | D1: Low | E1: Close | F1: Volume | G1: monthly_return
A2: 44439 | B2: 51.9 | C2: 56.948 | D2: 50.537 | E2: 56.919 | F2: 547487750
A3: 44469 | B3: 56.9 | C3: 61.9 | D3: 56.808 | E3: 61.034 | F3: 823382960 | G3: =(E4-E3)/E3 -> 0.13102533
A4: 44500 | B4: 60.424 | C4: 69.097 | D4: 59.468 | E4: 69.031 | F4: 985816200 | G4: =(E5-E4)/E4 -> -0.070127914
A5: 44530 | B5: 68.906 | C5: 70.0989 | D5: 64.001 | E5: 64.19 | F5: 645350910 | G5: =(E6-E5)/E5 -> -0.06147375
A6: 44561 | B6: 64.948 | C6: 65.452 | D6: 58.174 | E6: 60.244 | F6: 600388250 | G6: =(E7-E6)/E6 -> -0.29098333
A7: 44592 | B7: 60.561 | C7: 60.999 | D7: 35.146 | E7: 42.714 | F7: 2417094530 | G7: =(E8-E7)/E7 -> -0.076368404
A8: 44620 | B8: 43.296 | C8: 45.848 | D8: 35.472 | E8: 39.452 | F8: 1510141470 | G8: =(E9-E8)/E8 -> -0.050517084
A9: 44651 | B9: 39.16 | C9: 39.65 | D9: 32.982 | E9: 37.459 | F9: 1194970510 | G9: =(E10-E9)/E9 -> -0.49181772
A10: 44681 | B10: 37.68 | C10: 39.602 | D10: 18.56 | E10: 19.036 | F10: 4033328160 | G10: =(E11-E10)/E10 -> 0.037192688
A11: 44712 | B11: 19.171 | C11: 20.438 | D11: 16.271 | E11: 19.744 | F11: 2516159250 | G11: =(E12-E11)/E11 -> -0.11431321
A12: 44742 | B12: 19.87 | C12: 20.738 | D12: 16.428 | E12: 17.487 | F12: 1925961380 | G12: =(E13-E12)/E12 -> 0.28609824
A13: 44773 | B13: 17.649 | C13: 23.075 | D13: 16.9702 | E13: 22.49 | F13: 2700981560 | G13: =(E14-E13)/E13 -> -0.0059582036
A14: 44804 | B14: 22.3095 | C14: 25.199 | D14: 21.874 | E14: 22.356 | F14: 1522738240 | G14: =(E15-E14)/E14 -> 0.053140097
... A60: 46203 | B60: 85.725 | C60: 87.225 | D60: 70.86 | E60: 71.4 | F60: 1004130636 | G60: =(E61-E60)/E60 -> 0.0043417367
A61: 46234 | B61: 72.59 | C61: 78.44 | D61: 65.08 | E61: 71.71 | F61: 1080794897

Sheet SP500_fred_5yr
A1: observation_date | B1: SP500 | C1: monthly_return
A2: 44409 | B2: 4522.68
A3: 44440 | B3: 4307.54 | C3: =(B4-B3)/B3 -> 0.069143873
A4: 44470 | B4: 4605.38 | C4: =(B5-B4)/B4 -> -0.0083337314
A5: 44501 | B5: 4567 | C5: =(B6-B5)/B5 -> 0.043612875
A6: 44531 | B6: 4766.18 | C6: =(B7-B6)/B6 -> -0.052585089
A7: 44562 | B7: 4515.55 | C7: =(B8-B7)/B7 -> -0.031360521
A8: 44593 | B8: 4373.94 | C8: =(B9-B8)/B8 -> 0.035773239
A9: 44621 | B9: 4530.41 | C9: =(B10-B9)/B9 -> -0.087956719
A10: 44652 | B10: 4131.93 | C10: =(B11-B10)/B10 -> 5.3243884e-05
A11: 44682 | B11: 4132.15 | C11: =(B12-B11)/B11 -> -0.083919993
A12: 44713 | B12: 3785.38 | C12: =(B13-B12)/B12 -> 0.091116348
A13: 44743 | B13: 4130.29 | C13: =(B14-B13)/B13 -> -0.042440119
A14: 44774 | B14: 3955 | C14: =(B15-B14)/B14 -> -0.093395702
... A60: 46174 | B60: 7499.36 | C60: =(B61-B60)/B60 -> -0.001285443
A61: 46204 | B61: 7489.72

Sheet Red Notice
A1: line_item | B1: value | C1: source/formula | D1: notes
A2: production budget | B2: 200000000 | C2: the-numbers | D2: estimate ranges from $150M (The Numbers) to $300M (director's own account, Screenrant reporting)
A3: licensing cost | B3: N/A | D3: Netflix produced original, no licensing cost applies to this decision type
A4: marketing spend | B4: N/A | D4: Not disclosed for any title in this analysis; no reliable industry estimate exists for per-title marketing spend
A5: total investment | B5: 200000000 | C5: =B2 -> 200000000 | D5: Production budget only; marketing excluded per N/A above
A6: total hours viewed | B6: 454200000 | C6: Netflix Tudum | D6: First 91 days, all-time ranking; secondhand via press citing Tudum's official data
A7: attributable revenue | B7: 1.0688603e+08 | C7: =B6*0.235328125 -> 1.0688603e+08 | D7: Hours viewed x Value per Hour (from Metrics tab)
A8: licensing revenue | B8: N/A | D8: Not applicable, Netflix original
A9: total projected | B9: N/A | D9: This is a backtest against actual outcome data, not a forward-looking forecast; see README for methodology
A10: actual revenue | B10: 1.0688603e+08 | C10: =B7 -> 1.0688603e+08 | D10: 91-day window only; conservative floor, not lifetime value (see README)
A11: net cash flow | B11: -93113966 | D11: Actual revenue minus total investment, undiscounted
A12: discount rate | B12: 0.1079 | C12: Metrics tab (WACC)
A13: discount period (years) | B13: 0.24931507 | C13: =91/365 -> 0.24931507 | D13: 91-day window expressed in years for discounting
A14: present value of cash flow | B14: 1.0419006e+08
A15: npv | B15: -95809936
A16: payback period | B16: Not achieved within 91-day window | D16: 53.4% of investment recouped within observable 91-day window; true payback period exceeds available data and cannot be precisely determined

Sheet Extraction
A1: line_item | B1: value | C1: source/formula | D1: notes
A2: production budget | B2: 67500000 | C2: the-numbers | D2: Midpoint of \$65-70M reported range; Low confidence, unconfirmed/not officially disclosed
A3: licensing cost | B3: N/A | D3: Netflix produced original, no licensing cost applies to this decision type
A4: marketing spend | B4: N/A | D4: Not disclosed for any title in this analysis; no reliable industry estimate exists for per-title marketing spend
A5: total investment | B5: 67500000 | C5: =B2 -> 67500000 | D5: Production budget only; marketing excluded per N/A above
A6: total hours viewed (Extraction 1, informing precedent) | B6: 266900000 | C6: Netflix Tudum | D6: First 91 days; Extraction 1's real performance, used as the baseline precedent informing the Extraction 2 greenlight decision
A7: total projected revenue | B7: 62809077 | C7: =266900000*0.235328125 -> 62809077 | D7: Extraction 1's hours x Value per Hour; naive baseline expectation for the sequel based on the franchise's prior real performance
A8: total hours viewed (Extraction 2, actual) | B8: 278700000 | C8: Netflix Tudum | D8: First 91 days; Extraction 2's real outcome, used to validate the greenlight decision
A9: actual revenue | B9: 65585948 | C9: =278700000*0.235328125 -> 65585948 | D9: Extraction 2's hours x Value per Hour
A10: net cash flow | B10: -1914051.6 | D10: Actual revenue minus total investment, undiscounted
A11: discount rate | B11: 0.1079 | C11: Metrics tab (WACC)
A12: discount period (years) | B12: 0.24931507 | C12: =91/365 -> 0.24931507 | D12: 91-day window expressed in years for discounting
A13: present value of cash flow | B13: 63931684 | C13: =B9/(1+B11)^B12 -> 63931684
A14: npv | B14: -3568316.2
A15: payback period | B15: Not achieved within 91-day window | C15: 97.2% of investment recouped within observable 91-day window; true payback period exceeds available data
A16: payback period

Sheet Mario
A1: line_item | B1: value | C1: source/formula | D1: notes
A2: production budget | B2: N/A | D2: Financed by Illumination/Universal, not Netflix production cost
A3: licensing cost | B3: N/A | D3: Not publicly disclosed anywhere for this title; no reliable estimate exists. NPV and payback period cannot be calculated without this figure - see notes below
A4: marketing spend | B4: N/A | D4: Not applicable; Netflix did not market this as an original release
A5: total investment | B5: N/A | D5: Cannot be calculated; licensing cost undisclosed
A6: worldwide box office | B6: 1359226275 | C6: The Numbers | D6: Confirmed figure, audited box office data; theatrical performance prior to Netflix licensing, not a Netflix cash flow
A7: total hours viewed (debut week) | B7: 4800000 | C7: Netflix Tudum (via ScreenRant) | D7: Nov 27-Dec 3 2023, global, ranked #9
A8: total hours viewed (first 8 weeks, cumulative) | B8: 6500000 | C8: Netflix Tudum (via ScreenRant) | D8: Global, through late Jan 2024
A9: revenue estimate (8-week window) | B9: 1529632.8 | C9: =6500000*0.235328125 -> 1529632.8 | D9: Illustrates same 91-day-style understatement problem seen with Red Notice/Extraction, at a much more extreme scale
A10: total hours viewed (calendar year 2024, US only) | B10: 195300000 | C10: Statista/Nielsen | D10: Excludes Dec 2023 launch month and all non-US viewing; NOT global, understates true total
A11: revenue estimate (CY2024, US-only window) | B11: 45959583 | C11: =195300000*0.235328125 -> 45959583 | D11: Uses global value-per-hour rate against US-only hours - known scope mismatch, likely understates true value further since it excludes non-US engagement entirely
A12: netflix top 10 duration | B12: 38 | C12: Comcast/UFEG Press Release | D12: Primary source; record-setting run, Dec 2023-Oct 2024; full run extends well beyond both windows shown above
A13: npv | B13: N/A | D13: Cannot be calculated without licensing cost
A14: payback period | B14: N/A | D14: Cannot be calculated without licensing cost

Sheet Sensitivity
A1: Red Notice
A2: Value per Hour \ Discount Rate | B2: 0.08 | C2: 0.09 | D2: 10.79% (Base) | E2: 0.12 | F2: 0.14
A3: -0.2 | B3: -116116237 | C3: -116308768 | D3: -116647949 | E3: -116873373 | F3: -117239384
A4: -0.1 | B4: -105630766 | C4: -105847364 | D4: -106228943 | E4: -106482545 | F4: -106894307
A5: Base ($0.235328) | B5: -95145296 | C5: -95385960 | D5: -95809936 | E5: -96091717 | F5: -96549230
A6: 0.1 | B6: -84659826 | C6: -84924556 | D6: -85390930 | E6: -85700888 | F6: -86204153
A7: 0.2 | B7: -74174355 | C7: -74463152 | D7: -74971924 | E7: -75310060 | F7: -75859076
A10: Extraction
A11: Value per Hour \ Discount Rate | B11: 0.08 | C11: 0.09 | D11: 10.79% (Base) | E11: 0.12 | F11: 0.14
A12: -0.2 | B12: -16028391 | C12: -16146529 | D12: -16354653 | E12: -16492975 | F12: -16717561
A13: -0.1 | B13: -9594440 | C13: -9727345 | D13: -9961485 | E13: -10117097 | F13: -10369756
A14: Base ($0.235328) | B14: -3160489 | C14: -3308162 | D14: -3568316 | E14: -3741219 | F14: -4021952
A15: 0.1 | B15: 3273462 | C15: 3111022 | D15: 2824852 | E15: 2634660 | F15: 2325853
A16: 0.2 | B16: 9707413 | C16: 9530206 | D16: 9218021 | E16: 9010538 | F16: 8673658
A19: Mario
A20: Value per Hour \ Hours-Viewed Window | B20: 8-week (6.5M hrs) | C20: CY2024 US-only (195.3M hrs)
A21: -0.2 | B21: 1223706 | C21: 36767666
A22: -0.1 | B22: 1376670 | C22: 41363625
A23: Base ($0.235328) | B23: 1529633 | C23: 45959583
A24: 0.1 | B24: 1682596 | C24: 50555541
A25: 0.2 | B25: 1835559 | C25: 55151499

Sheet Go or No Go Summary
A1: title | B1: decision_type | C1: investment_cost | D1: npv | E1: payback_period | F1: recommendation | G1: key_risk_factor | H1: rationale
A2: Red Notice | B2: Original content greenlight (retrospective backtest) | C2: 200000000 | D2: -95809936 | E2: Not achieved within 91-day window (53.4% recouped) | F2: GO, with caveat | G2: 91-day NPV is a known conservative floor, not a lifetime estimate; true economics beyond the observable window are unknown from public data | H2: 91-day NPV is negative, but this window structurally understates value (content amortized over years per Netflix's own accounting, Note 5 of 10-Q). Real-world evidence strongly supports a positive lifetime NPV: became Netflix's most-watched film for several years, remained in the all-time Top 10, and Netflix itself greenlit a sequel - a strong revealed-preference signal the studio views the original as having paid off
A3: Extraction | B3: Franchise continuation greenlight (retrospective backtest, Extraction 2) | C3: 67500000 | D3: -3568316 | E3: Not achieved within 91-day window (97.2% recouped) | F3: GO | G3: NPV is highly sensitive to Value per Hour assumption - flips positive at only +10% off base case | H3: Nearly broke even within the conservative 91-day window alone (97.2% recouped), a meaningfully stronger result than Red Notice's. Given the same understatement bias applies here, true lifetime NPV is very likely positive. Extraction 2 also outperformed Extraction 1 (278.7M vs 266.9M hours), validating the precedent the continuation decision was based on
A4: The Super Mario Bros Movie | B4: Licensing/streaming rights acquisition (retrospective, real deal already executed by Netflix) | C4: N/A - licensing cost not publicly disclosed | D4: N/A - cannot calculate without cost figure | E4: N/A - cannot calculate without cost figure | F4: Cannot be formally assessed via NPV; qualitative evidence supports the actual decision | G4: No public licensing cost figure exists for this or any comparable title in the UFEG output deal; industry-standard rate-card structure confirmed but rate itself undisclosed | H4: NPV/payback cannot be computed without a cost input. However, real engagement data is compelling on its own: record-setting 38-week Top 10 run, and CY2024 US-only engagement alone (195.3M hours) was ~30x the initial 8-week figure - a clear illustration that licensed library content compounds value over a much longer horizon than the 91-day metric used elsewhere in this model

Sheet README
A2: Data sourcing
A3: Confidence tier definitions
A4: High | B4: primary source (filling, official report, audited box office)
A5: Medium | B5: reputable trade press with attributed sourcing
A6: Low | B6: single non-corroborated source, wide estimate range or derived modeled figure
A8: Individual title production budgets are not disclosed in SEC filings for any studio; trade press estimates are the standard and only available source for this category, and are corroborated across multiple outlets per title.
A11: Sources
A12: The Numbers | B12: https://www.the-numbers.com/
A13: Netflix Q4 2025 Earnings Letter | B13: https://ir.netflix.net/investor-news-and-events/investor-events/event-details/2026/Netflix-Fourth-Quarter-2025-Earnings-Interview-2026-ILhOSSH43f/default.aspx
B14: https://s22.q4cdn.com/959853165/files/doc_financials/2025/q4/FINAL-Q4-25-Shareholder-Letter.pdf
A15: Netflix Investor 10-Q & 10-K filings | B15: https://ir.netflix.net/financials/sec-filings/default.aspx
A16: 10-Q Filing | B16: https://d18rn0p25nwr6d.cloudfront.net/CIK-0001065280/65ef36cc-6598-4deb-a42b-8c59a8e31fd3.pdf
A17: 10-K Filing | B17: https://d18rn0p25nwr6d.cloudfront.net/CIK-0001065280/99482238-46b2-4d0d-b292-40e6781bdf03.pdf
A18: Stooq | B18: https://stooq.com/
A19: FRED | B19: https://fred.stlouisfed.org/series/SP500#
A20: Damodaran Implied ERP (Historical Series) | B20: https://pages.stern.nyu.edu/~adamodar/New_Home_Page/datafile/histimpl.html
A21: Netflix Tudum (Top 10 - Most Popular Movies) | B21: https://www.netflix.com/tudum/top10/most-popular
A22: CBR - Netflix Most-Watched Movies of All Time | B22: https://www.cbr.com/netflix-most-watched-movies-all-time/
A23: Collider - Netflix Most-Streamed Movies of All Time | B23: https://collider.com/netflix-most-watched-movies-all-time-kpop-demon-hunters-red-notice-carry-on/
A24: What's on Netflix - Extraction Franchise Coverage | B24: https://www.whats-on-netflix.com/coming-soon/new-extraction-movies-series-coming-to-netflxi/
A25: Wikipedia - Carry-On (2024) | B25: https://en.wikipedia.org/wiki/Carry-On
A26: IMDb - Carry-On (2024) FAQ | B26: https://www.imdb.com/title/tt21382296/faq/
... A42: Deadline - Netflix-Sony $7B Pay-1 Deal | B42: https://deadline.com/2026/01/netflix-sony-pictures-deal-pay-1-1236684173/
A45: Discount Rate Methodology
A46: This model uses Netflix's WACC (10.79%) as the discount rate for all three titles, rather than adding a project-specific risk premium. The reasoning: discount rates are meant to price in systematic risk the part of a project's risk that moves with the broader market not idiosyncratic risk, which is specific to one title and doesn't require compensation in the rate itself because it's diversifiable across Netflix's full content slate. Whether Red Notice or Extraction 2 hits or flops depends mostly on title-specific factors (marketing, competition, reception), not market correlation, so that risk belongs in the cash flow assumptions, not the discount rate. This model addresses it through the sensitivity analysis instead testing a range of outcomes rather than inflating the rate used to discount them.
A48: This model relies exclusively on public data sources, since internal Netflix engagement and financial systems aren't accessible externally. A production analyst in this role would have access to richer internal data (granular subscriber attribution, unredacted budgets, cross-era-consistent engagement tracking) that would resolve several of the constraints documented here — but the underlying analytical approach (comps-based forecasting, methodology-consistency checks, defensible confidence tiering) mirrors how that internal data would be used.
A50: licensing cost N/A | B50: Industry-standard licensing deals of this type (e.g., Netflix-Sony pay-1 deal) are confirmed to use box-office-linked rate cards, per Deadline reporting. However, no specific rate or per-title dollar figure has been publicly disclosed for the Universal/Illumination/DreamWorks deal under which Mario was licensed. A defensible cost estimate cannot be constructed without a rate figure that doesn't exist in public sources.
A52: Comps Based Forecasting | B52: A comps-based forecast for Red Notice (predicting hours viewed from production budget, using 8 comparable Netflix action/thriller originals) was tested and found statistically insignificant (R² = 0.031, p = 0.677). This is a genuine finding, not a methodology failure: budget alone is not a reliable predictor of streaming engagement, since success depends more on marketing, star power, timing, and reception than raw production cost. Rather than force a fabricated point estimate, this model instead evaluates each title as a retrospective backtest against real, sourced outcome data (Netflix Tudum's official 91-day hours-viewed figures).
A54: Comp Set Size Limitation | B54: Netflix changed its public engagement-tracking methodology in November 2021, from "households reached in 28 days" to "hours viewed in 91 days." Titles released before that date have no data in the current metric not withheld, never measured under this standard. Additionally, Netflix's official 91-day rankings are only ever published for currently-ranked titles; once a title falls out of the all-time Top 10, its figure is generally no longer republished. Both factors impose a structural ceiling on the size of a same-methodology comp set obtainable from public sources.
A56: Value Per Hour | B56: The Value per Hour figure ($0.235328) was cross-checked against an independent calculation: content amortization expense (10-Q, Note 5) divided by platform-wide hours viewed (Q4'25 Shareholder Letter). This yields a cost-per-hour of approximately $0.089 meaning revenue-per-hour exceeds cost-per-hour by roughly 2.65x, directionally consistent with Netflix's reported operating margin and cost structure. Note: the two figures compared are drawn from slightly offset reporting periods (six months ended June 30, 2026 vs. H2 2025), so this is a directional validation, not a precisely period-matched one.
A58: Mario's Structural Notes | B58: Mario's tab is structured differently from Red Notice and Extraction because it represents a fundamentally different decision type: a licensing/streaming-rights acquisition of an already-independently-monetized title (full theatrical run and box office prior to any Netflix involvement), versus a decision to finance new production for direct streaming. Mario's licensing cost is not publicly disclosed for this or any comparable title under the Universal/Illumination/DreamWorks output deal; industry-standard practice for this deal type is confirmed to use box-office-linked rate cards (per Netflix-Sony pay-1 deal reporting), but no specific rate has been disclosed, so a defensible cost estimate cannot be constructed. NPV and payback period are therefore not calculable for this title; the analysis instead presents real engagement data as qualitative evidence.
A60: 91-Day window as a conservative floor | B60: All hours-viewed figures for Red Notice and Extraction reflect Netflix's official 91-day measurement window, which understates total lifetime engagement value. This is best illustrated by Mario's real engagement data: its first-8-week hours-viewed figure (6.5M) is roughly 30x smaller than its calendar-year-2024 (US-only) figure alone (195.3M) and the true full-run total, across its record 38-week Top 10 run, is higher still. NPV figures throughout this model should be read as conservative floors, not lifetime estimates, consistent with how Netflix's own accounting recognizes content value over an extended amortization period rather than at a single point in time (10-Q, Note 5).
